{
  "project_info": {
    "project_number": "624789699023",
    "firebase_url": "https://jamja-android-dev.firebaseio.com",
    "project_id": "jamja-android-dev",
    "storage_bucket": "jamja-android-dev.appspot.com"
  },
  "client": [
    {
      "client_info": {
        "mobilesdk_app_id": "1:624789699023:android:059953f8abefaf85",
        "android_client_info": {
          "package_name": "com.jamjavn.jamjadev"
        }
      },
      "oauth_client": [
        {
          "client_id": "624789699023-8clfelec0idre3tabmvs77nbfuvh9ddv.apps.googleusercontent.com",
          "client_type": 3
        }
      ],
      "api_key": [
        {
          "current_key": "AIzaSyByAml8GhCxNVkaj0RvFvhjI56QNJvEKWw"
        }
      ],
      "services": {
        "analytics_service": {
          "status": 1
        },
        "appinvite_service": {
          "status": 1,
          "other_platform_oauth_client": []
        },
        "ads_service": {
          "status": 2
        }
      }
    },
    {
      "client_info": {
        "mobilesdk_app_id": "1:624789699023:android:bb8112608615cd3a",
        "android_client_info": {
          "package_name": "com.bvlab.screenrecord"
        }
      },
      "oauth_client": [
        {
          "client_id": "624789699023-8clfelec0idre3tabmvs77nbfuvh9ddv.apps.googleusercontent.com",
          "client_type": 3
        }
      ],
      "api_key": [
        {
          "current_key": "AIzaSyByAml8GhCxNVkaj0RvFvhjI56QNJvEKWw"
        }
      ],
      "services": {
        "analytics_service": {
          "status": 1
        },
        "appinvite_service": {
          "status": 1,
          "other_platform_oauth_client": []
        },
        "ads_service": {
          "status": 2
        }
      }
    }
  ],
  "configuration_version": "1"
}